{
	"metadata": [
			{
				"filename": "001.jpg",
				"startTime": "2020-03-09T19:42:00.000Z",
				"endTime": "2020-03-09T19:52:00.000Z",
				"caption": "a close up of a pair of scissors on a table"
			},
			{
				"filename": "002.jpg",
				"startTime": "2020-03-26T19:41:00.000Z",
				"endTime": "2020-03-26T19:53:00.000Z",
				"caption": "a close up of a person holding an apple"
			},
			{
				"filename": "003.jpg",
				"startTime": "2020-03-28T19:56:00.000Z",
				"endTime": "2020-03-28T20:06:00.000Z",
				"caption": "a close up of an orange in a tree"
			},
			{
				"filename": "004.jpg",
				"startTime": "2020-04-03T20:33:00.000Z",
				"endTime": "2020-04-03T20:43:00.000Z",
				"caption": "a black and white photo of a snow covered mountain"
			},
			{
				"filename": "005.jpg",
				"startTime": "2020-04-03T20:48:00.000Z",
				"endTime": "2020-04-03T20:58:00.000Z",
				"caption": "a close up of a plant in a tree"
			},
			{
				"filename": "006.jpg",
				"startTime": "2020-04-15T18:47:00.000Z",
				"endTime": "2020-04-15T18:57:00.000Z",
				"caption": "a black and white photo of a pair of scissors"
			},
			{
				"filename": "007.jpg",
				"startTime": "2020-04-15T19:02:00.000Z",
				"endTime": "2020-04-15T19:12:00.000Z",
				"caption": "a close up of a person holding an umbrella"
			},
			{
				"filename": "008.jpg",
				"startTime": "2020-04-15T19:19:00.000Z",
				"endTime": "2020-04-15T19:29:00.000Z",
				"caption": "a close up of a person holding an umbrella"
			},
			{
				"filename": "009.jpg",
				"startTime": "2020-04-15T20:10:00.000Z",
				"endTime": "2020-04-15T20:20:00.000Z",
				"caption": "a close up of a plant in a body of water"
			},
			{
				"filename": "010.jpg",
				"startTime": "2020-04-15T20:24:00.000Z",
				"endTime": "2020-04-15T20:34:00.000Z",
				"caption": "a close up of a plant in a body of water"
			},
			{
				"filename": "011.jpg",
				"startTime": "2020-05-07T17:32:00.000Z",
				"endTime": "2020-05-07T17:42:00.000Z",
				"caption": "a close up of a plant in a vase"
			},
			{
				"filename": "012.jpg",
				"startTime": "2020-05-07T18:24:00.000Z",
				"endTime": "2020-05-07T18:34:00.000Z",
				"caption": "a black and white photo of a snow-capped mountain"
			},
			{
				"filename": "013.jpg",
				"startTime": "2020-05-07T18:40:00.000Z",
				"endTime": "2020-05-07T18:50:00.000Z",
				"caption": "a close up of a bird in a tree"
			},
			{
				"filename": "014.jpg",
				"startTime": "2020-05-07T22:13:00.000Z",
				"endTime": "2020-05-07T22:23:00.000Z",
				"caption": "a large jetliner flying over a mountain range"
			},
			{
				"filename": "015.jpg",
				"startTime": "2020-05-07T22:27:00.000Z",
				"endTime": "2020-05-07T22:37:00.000Z",
				"caption": "a black and white photo of a person holding an umbrella"
			},
			{
				"filename": "016.jpg",
				"startTime": "2020-05-07T22:41:00.000Z",
				"endTime": "2020-05-07T22:52:00.000Z",
				"caption": "a white and black bird with an orange beak"
			},
			{
				"filename": "017.jpg",
				"startTime": "2020-05-07T22:54:00.000Z",
				"endTime": "2020-05-07T23:04:00.000Z",
				"caption": "a black and white photo of a person flying a kite"
			},
			{
				"filename": "018.jpg",
				"startTime": "2020-05-07T23:12:00.000Z",
				"endTime": "2020-05-07T23:23:00.000Z",
				"caption": "a close up of a pair of scissors on a table"
			},
			{
				"filename": "019.jpg",
				"startTime": "2020-05-07T23:25:00.000Z",
				"endTime": "2020-05-07T23:35:00.000Z",
				"caption": "a close up of a person holding an apple"
			},
			{
				"filename": "020.jpg",
				"startTime": "2020-05-08T17:55:00.000Z",
				"endTime": "2020-05-08T18:05:00.000Z",
				"caption": "a close up of a vase with a plant in it"
			},
			{
				"filename": "021.jpg",
				"startTime": "2020-05-08T18:10:00.000Z",
				"endTime": "2020-05-08T18:20:00.000Z",
				"caption": "a close up of an orange in a tree"
			},
			{
				"filename": "022.jpg",
				"startTime": "2020-05-08T18:24:00.000Z",
				"endTime": "2020-05-08T18:34:00.000Z",
				"caption": "a close up of a plant in a body of water"
			},
			{
				"filename": "023.jpg",
				"startTime": "2020-05-08T18:44:00.000Z",
				"endTime": "2020-05-08T18:54:00.000Z",
				"caption": "a close up of an orange and a knife"
			},
			{
				"filename": "024.jpg",
				"startTime": "2020-05-08T18:57:00.000Z",
				"endTime": "2020-05-08T19:08:00.000Z",
				"caption": "a close up of a bird on a windowsill"
			},
			{
				"filename": "025.jpg",
				"startTime": "2020-05-08T19:09:00.000Z",
				"endTime": "2020-05-08T19:19:00.000Z",
				"caption": "a close up of a person holding an umbrella"
			},
			{
				"filename": "026.jpg",
				"startTime": "2020-05-08T19:20:00.000Z",
				"endTime": "2020-05-08T19:30:00.000Z",
				"caption": "a black and white photo of a pair of scissors"
			},
			{
				"filename": "027.jpg",
				"startTime": "2020-05-08T17:36:00.000Z",
				"endTime": "2020-05-08T17:46:00.000Z",
				"caption": "a close up of a person holding an umbrella"
			},
			{
				"filename": "028.jpg",
				"startTime": "2020-05-08T19:43:00.000Z",
				"endTime": "2020-05-08T19:53:00.000Z",
				"caption": "a close up of an apple in a tree"
			},
			{
				"filename": "029.jpg",
				"startTime": "2020-05-08T20:31:00.000Z",
				"endTime": "2020-05-08T20:40:00.000Z",
				"caption": "a close up of a bird on a tree branch"
			},
			{
				"filename": "030.jpg",
				"startTime": "2020-06-13T18:03:00.000Z",
				"endTime": "2020-06-13T18:14:00.000Z",
				"caption": "a black and white photo of a vase of flowers"
			},
			{
				"filename": "031.jpg",
				"startTime": "2020-06-13T18:18:00.000Z",
				"endTime": "2020-06-13T18:28:00.000Z",
				"caption": "a close up of a bird on a tree branch"
			},
			{
				"filename": "032.jpg",
				"startTime": "2020-06-13T18:31:00.000Z",
				"endTime": "2020-06-13T18:41:00.000Z",
				"caption": "a close up of a bunch of green bananas"
			},
			{
				"filename": "033.jpg",
				"startTime": "2020-06-13T21:13:00.000Z",
				"endTime": "2020-06-13T21:23:00.000Z",
				"caption": "a close up of a pair of scissors in the air"
			},
			{
				"filename": "034.jpg",
				"startTime": "2020-06-13T21:28:00.000Z",
				"endTime": "2020-06-13T21:38:00.000Z",
				"caption": "a black and white photo of a person holding an umbrella"
			},
			{
				"filename": "035.jpg",
				"startTime": "2020-08-11T21:02:00.000Z",
				"endTime": "2020-08-11T21:10:00.000Z",
				"caption": "a close up of an apple on a tree"
			},
			{
				"filename": "036.jpg",
				"startTime": "2020-08-28T19:35:00.000Z",
				"endTime": "2020-08-28T19:42:00.000Z",
				"caption": "a close up of an apple on a table"
			},
			{
				"filename": "037.jpg",
				"startTime": "2020-08-28T19:47:00.000Z",
				"endTime": "2020-08-28T19:54:00.000Z",
				"caption": "a close up of an apple in a tree"
			},
			{
				"filename": "038.jpg",
				"startTime": "2020-08-28T21:25:00.000Z",
				"endTime": "2020-08-28T21:32:00.000Z",
				"caption": "a close up of a pair of scissors on a table"
			},
			{
				"filename": "039.jpg",
				"startTime": "2020-08-28T21:36:00.000Z",
				"endTime": "2020-08-28T21:43:00.000Z",
				"caption": "a close up of a pair of scissors on a table"
			},
			{
				"filename": "040.jpg",
				"startTime": "2020-08-28T21:48:00.000Z",
				"endTime": "2020-08-28T21:55:00.000Z",
				"caption": "a black and white image of a bird on a rock"
			},
			{
				"filename": "041.jpg",
				"startTime": "2020-08-28T22:02:00.000Z",
				"endTime": "2020-08-28T22:09:00.000Z",
				"caption": "a close up of a pair of red scissors"
			},
			{
				"filename": "042.jpg",
				"startTime": "2020-09-26T19:04:00.000Z",
				"endTime": "2020-09-26T:19:16:00.000Z",
				"caption": "a close up of a person holding an apple"
			},
			{
				"filename": "043.jpg",
				"startTime": "2020-09-26T19:33:00.000Z",
				"endTime": "2020-09-26T19:45:00.000Z",
				"caption": "a black and white photo of a bird on a rock"
			},
			{
				"filename": "044.jpg",
				"startTime": "2020-09-26T20:02:00.000Z",
				"endTime": "2020-09-26T20:14:00.000Z",
				"caption": "a close up of a pair of scissors on a table"
			},
			{
				"filename": "045.jpg",
				"startTime": "2020-09-26T20:19:00.000Z",
				"endTime": "2020-09-26T20:31:00.000Z",
				"caption": "a black and white photo of a person holding an umbrella"
			},
			{
				"filename": "046.jpg",
				"startTime": "2020-09-26T20:36:00.000Z",
				"endTime": "2020-09-26T20:50:00.000Z",
				"caption": "a close up of a person holding an umbrella"
			},
			{
				"filename": "047.jpg",
				"startTime": "2020-09-26T20:43:00.000Z",
				"endTime": "2020-09-26T20:53:00.000Z",
				"caption": "a black and white photo of a pair of scissors"
			},
			{
				"filename": "048.jpg",
				"startTime": "2020-09-26T20:52:00.000Z",
				"endTime": "2020-09-26T21:04:00.000Z",
				"caption": "a close up of a red and white bird"
			},
			{
				"filename": "049.jpg",
				"startTime": "2020-09-26T21:06:00.000Z",
				"endTime": "2020-09-26T21:18:00.000Z",
				"caption": "a close up of a person holding a knife"
			},
			{
				"filename": "050.jpg",
				"startTime": "2020-09-26T21:10:00.000Z",
				"endTime": "2020-09-26T21:23:00.000Z",
				"caption": "a close up of a bunch of green apples"
			},
			{
				"filename": "051.jpg",
				"startTime": "2020-09-26T21:27:00.000Z",
				"endTime": "2020-09-26T21:39:00.000Z",
				"caption": "a black and white photo of a pair of scissors"
			},
			{
				"filename": "052.jpg",
				"startTime": "2020-09-28T19:29:00.000Z",
				"endTime": "2020-09-28T19:38:00.000Z",
				"caption": "a black and white photo of a plane flying in the sky"
			},
			{
				"filename": "053.jpg",
				"startTime": "2020-09-28T19:43:00.000Z",
				"endTime": "2020-09-28T19:53:00.000Z",
				"caption": "a black and white photo of a person holding an umbrella"
			},
			{
				"filename": "054.jpg",
				"startTime": "2020-09-28T19:58:00.000Z",
				"endTime": "2020-09-28T20:09:00.000Z",
				"caption": "a black and white photo of a pair of scissors"
			},
			{
				"filename": "055.jpg",
				"startTime": "2020-09-28T20:12:00.000Z",
				"endTime": "2020-09-28T20:22:00.000Z",
				"caption": "a person is skiing down a snowy hill"
			},
			{
				"filename": "056.jpg",
				"startTime": "2020-09-28T20:27:00.000Z",
				"endTime": "2020-09-28T20:37:00.000Z",
				"caption": "a close up of a pair of skis on a snowy surface"
			},
			{
				"filename": "057.jpg",
				"startTime": "2020-09-28T20:58:00.000Z",
				"endTime": "2020-09-28T21:08:00.000Z",
				"caption": "a close up of a bird in a tree"
			},
			{
				"filename": "058.jpg",
				"startTime": "2020-09-28T21:24:00.000Z",
				"endTime": "2020-09-28T21:34:00.000Z",
				"caption": "a black and white photo of a pair of scissors"
			},
			{
				"filename": "059.jpg",
				"startTime": "2020-09-28T21:54:00.000Z",
				"endTime": "2020-09-28T22:04:00.000Z",
				"caption": "a black and white photo of a pair of scissors"
			},
			{
				"filename": "060.jpg",
				"startTime": "2020-09-28T22:10:00.000Z",
				"endTime": "2020-09-28T22:20:00.000Z",
				"caption": "a bird is sitting on top of a bird feeder"
			},
			{
				"filename": "061.jpg",
				"startTime": "2020-09-28T22:29:00.000Z",
				"endTime": "2020-09-28T22:39:00.000Z",
				"caption": "a black and white photo of a person holding an umbrella"
			},
			{
				"filename": "062.jpg",
				"startTime": "2020-09-28T22:46:00.000Z",
				"endTime": "2020-09-28T22:57:00.000Z",
				"caption": "a black and white photo of a pair of scissors"
			},
			{
				"filename": "063.jpg",
				"startTime": "2020-09-28T23:01:00.000Z",
				"endTime": "2020-09-28T23:11:00.000Z",
				"caption": "a black and white photo of a person holding an umbrella"
			},
			{
				"filename": "064.jpg",
				"startTime": "2020-09-28T23:18:00.000Z",
				"endTime": "2020-09-28T23:28:00.000Z",
				"caption": "a close up of a person holding an apple"
			},
			{
				"filename": "065.jpg",
				"startTime": "2020-09-28T23:35:00.000Z",
				"endTime": "2020-09-28T23:46:00.000Z",
				"caption": "a close up of a bird on a tree"
			},
			{
				"filename": "066.jpg",
				"startTime": "2020-10-12T19:34:00.000Z",
				"endTime": "2020-10-12T19:41:00.000Z",
				"caption": "a black and white photo of a person holding an umbrella"
			},
			{
				"filename": "067.jpg",
				"startTime": "2020-10-12T19:54:00.000Z",
				"endTime": "2020-10-12T20:02:00.000Z",
				"caption": "a black and white photo of a plane flying in the sky"
			},
			{
				"filename": "068.jpg",
				"startTime": "2020-10-12T20:03:00.000Z",
				"endTime": "2020-10-12T20:11:00.000Z",
				"caption": "a black and white photo of a vase with flowers"
			},
			{
				"filename": "069.jpg",
				"startTime": "2020-10-12T20:17:00.000Z",
				"endTime": "2020-10-12T20:25:00.000Z",
				"caption": "a close up of a person holding an umbrella"
			},
			{
				"filename": "070.jpg",
				"startTime": "2020-10-12T21:08:00.000Z",
				"endTime": "2020-10-12T21:15:00.000Z",
				"caption": "a close up of a plant in a tree"
			},
			{
				"filename": "071.jpg",
				"startTime": "2020-10-12T21:23:00.000Z",
				"endTime": "2020-10-12T21:29:00.000Z",
				"caption": "a close up of a plant in a garden"
			},
			{
				"filename": "072.jpg",
				"startTime": "2020-10-12T21:36:00.000Z",
				"endTime": "2020-10-12T21:43:00.000Z",
				"caption": "a close up of a plant in a tree"
			},
			{
				"filename": "073.jpg",
				"startTime": "2020-10-12T21:50:00.000Z",
				"endTime": "2020-10-12T21:58:00.000Z",
				"caption": "a close up of a person holding an apple"
			},
			{
				"filename": "074.jpg",
				"startTime": "2020-10-12T22:04:00.000Z",
				"endTime": "2020-10-12T22:12:00.000Z",
				"caption": "a close up of a bird on a tree branch"
			},
			{
				"filename": "075.jpg",
				"startTime": "2020-10-12T22:29:00.000Z",
				"endTime": "2020-10-12T22:37:00.000Z",
				"caption": "a close up of a plant in a garden"
			},
			{
				"filename": "076.jpg",
				"startTime": "2020-10-12T22:41:00.000Z",
				"endTime": "2020-10-12T22:51:00.000Z",
				"caption": "a green plant that is growing in the grass"
			},
			{
				"filename": "077.jpg",
				"startTime": "2020-10-12T23:22:00.000Z",
				"endTime": "2020-10-12T23:30:00.000Z",
				"caption": "a close up of a green and green plant"
			}
	]
}